{
   "lat":28.6139,
   "lon":77.209,
   "timezone":"Asia/Kolkata",
   "timezone_offset":19800,
   "current":{
	  "dt":1647976636,
	  "sunrise":1647996721,
	  "sunset":1648040616,
	  "temp":299.22,
	  "feels_like":299.22,
	  "pressure":1008,
	  "humidity":57,
	  "dew_point":290.04,
	  "uvi":0,
	  "clouds":0,
	  "visibility":3500,
	  "wind_speed":1.54,
	  "wind_deg":320,
	  "weather":[
		 {
			"id":721,
			"main":"Haze",
			"description":"haze",
			"icon":"50n"
		 }
	  ]
   },
   "hourly":[
	  {
		 "dt":1647975600,
		 "temp":299.22,
		 "feels_like":299.22,
		 "pressure":1008,
		 "humidity":57,
		 "dew_point":290.04,
		 "uvi":0,
		 "clouds":0,
		 "visibility":10000,
		 "wind_speed":2.91,
		 "wind_deg":281,
		 "wind_gust":8.37,
		 "weather":[
			{
			   "id":800,
			   "main":"Clear",
			   "description":"clear sky",
			   "icon":"01n"
			}
		 ],
		 "pop":0
	  },
	  {
		 "dt":1647979200,
		 "temp":299.33,
		 "feels_like":299.33,
		 "pressure":1008,
		 "humidity":47,
		 "dew_point":287.14,
		 "uvi":0,
		 "clouds":0,
		 "visibility":10000,
		 "wind_speed":2.46,
		 "wind_deg":302,
		 "wind_gust":7.59,
		 "weather":[
			{
			   "id":800,
			   "main":"Clear",
			   "description":"clear sky",
			   "icon":"01n"
			}
		 ],
		 "pop":0
	  },
	  {
		 "dt":1647982800,
		 "temp":299.16,
		 "feels_like":299.16,
		 "pressure":1008,
		 "humidity":38,
		 "dew_point":283.76,
		 "uvi":0,
		 "clouds":0,
		 "visibility":10000,
		 "wind_speed":2.41,
		 "wind_deg":307,
		 "wind_gust":7.02,
		 "weather":[
			{
			   "id":800,
			   "main":"Clear",
			   "description":"clear sky",
			   "icon":"01n"
			}
		 ],
		 "pop":0
	  },
	  {
		 "dt":1647986400,
		 "temp":298.79,
		 "feels_like":298.19,
		 "pressure":1007,
		 "humidity":30,
		 "dew_point":279.94,
		 "uvi":0,
		 "clouds":0,
		 "visibility":10000,
		 "wind_speed":2.68,
		 "wind_deg":295,
		 "wind_gust":6.62,
		 "weather":[
			{
			   "id":800,
			   "main":"Clear",
			   "description":"clear sky",
			   "icon":"01n"
			}
		 ],
		 "pop":0
	  },
	  {
		 "dt":1647990000,
		 "temp":298.16,
		 "feels_like":297.26,
		 "pressure":1007,
		 "humidity":21,
		 "dew_point":274.34,
		 "uvi":0,
		 "clouds":0,
		 "visibility":10000,
		 "wind_speed":2.7,
		 "wind_deg":293,
		 "wind_gust":6.21,
		 "weather":[
			{
			   "id":800,
			   "main":"Clear",
			   "description":"clear sky",
			   "icon":"01n"
			}
		 ],
		 "pop":0
	  },
	  {
		 "dt":1647993600,
		 "temp":297.46,
		 "feels_like":296.26,
		 "pressure":1007,
		 "humidity":12,
		 "dew_point":266.41,
		 "uvi":0,
		 "clouds":0,
		 "visibility":10000,
		 "wind_speed":2.5,
		 "wind_deg":289,
		 "wind_gust":5.28,
		 "weather":[
			{
			   "id":800,
			   "main":"Clear",
			   "description":"clear sky",
			   "icon":"01n"
			}
		 ],
		 "pop":0
	  },
	  {
		 "dt":1647997200,
		 "temp":297.09,
		 "feels_like":295.85,
		 "pressure":1008,
		 "humidity":12,
		 "dew_point":265.85,
		 "uvi":0,
		 "clouds":0,
		 "visibility":10000,
		 "wind_speed":2.8,
		 "wind_deg":282,
		 "wind_gust":5.62,
		 "weather":[
			{
			   "id":800,
			   "main":"Clear",
			   "description":"clear sky",
			   "icon":"01d"
			}
		 ],
		 "pop":0
	  },
	  {
		 "dt":1648000800,
		 "temp":298.2,
		 "feels_like":297.05,
		 "pressure":1008,
		 "humidity":11,
		 "dew_point":265.88,
		 "uvi":0.54,
		 "clouds":0,
		 "visibility":10000,
		 "wind_speed":2.5,
		 "wind_deg":290,
		 "wind_gust":5.35,
		 "weather":[
			{
			   "id":800,
			   "main":"Clear",
			   "description":"clear sky",
			   "icon":"01d"
			}
		 ],
		 "pop":0
	  },
	  {
		 "dt":1648004400,
		 "temp":300.82,
		 "feels_like":299.51,
		 "pressure":1009,
		 "humidity":10,
		 "dew_point":266.18,
		 "uvi":1.92,
		 "clouds":0,
		 "visibility":10000,
		 "wind_speed":4.01,
		 "wind_deg":284,
		 "wind_gust":6.34,
		 "weather":[
			{
			   "id":800,
			   "main":"Clear",
			   "description":"clear sky",
			   "icon":"01d"
			}
		 ],
		 "pop":0
	  },
	  {
		 "dt":1648008000,
		 "temp":303.27,
		 "feels_like":301.41,
		 "pressure":1009,
		 "humidity":9,
		 "dew_point":266.96,
		 "uvi":4.13,
		 "clouds":0,
		 "visibility":10000,
		 "wind_speed":3.83,
		 "wind_deg":285,
		 "wind_gust":5.89,
		 "weather":[
			{
			   "id":800,
			   "main":"Clear",
			   "description":"clear sky",
			   "icon":"01d"
			}
		 ],
		 "pop":0
	  },
	  {
		 "dt":1648011600,
		 "temp":306.08,
		 "feels_like":303.71,
		 "pressure":1009,
		 "humidity":8,
		 "dew_point":267.65,
		 "uvi":6.61,
		 "clouds":0,
		 "visibility":10000,
		 "wind_speed":3.82,
		 "wind_deg":282,
		 "wind_gust":5.62,
		 "weather":[
			{
			   "id":800,
			   "main":"Clear",
			   "description":"clear sky",
			   "icon":"01d"
			}
		 ],
		 "pop":0
	  },
	  {
		 "dt":1648015200,
		 "temp":308.42,
		 "feels_like":305.67,
		 "pressure":1008,
		 "humidity":7,
		 "dew_point":267.89,
		 "uvi":8.49,
		 "clouds":0,
		 "visibility":10000,
		 "wind_speed":3.33,
		 "wind_deg":284,
		 "wind_gust":5.54,
		 "weather":[
			{
			   "id":800,
			   "main":"Clear",
			   "description":"clear sky",
			   "icon":"01d"
			}
		 ],
		 "pop":0
	  },
	  {
		 "dt":1648018800,
		 "temp":309.98,
		 "feels_like":306.96,
		 "pressure":1007,
		 "humidity":6,
		 "dew_point":267.56,
		 "uvi":9.04,
		 "clouds":0,
		 "visibility":10000,
		 "wind_speed":3.46,
		 "wind_deg":291,
		 "wind_gust":6.37,
		 "weather":[
			{
			   "id":800,
			   "main":"Clear",
			   "description":"clear sky",
			   "icon":"01d"
			}
		 ],
		 "pop":0
	  },
	  {
		 "dt":1648022400,
		 "temp":310.81,
		 "feels_like":307.64,
		 "pressure":1006,
		 "humidity":6,
		 "dew_point":266.7,
		 "uvi":8.09,
		 "clouds":0,
		 "visibility":10000,
		 "wind_speed":3.95,
		 "wind_deg":296,
		 "wind_gust":6.49,
		 "weather":[
			{
			   "id":800,
			   "main":"Clear",
			   "description":"clear sky",
			   "icon":"01d"
			}
		 ],
		 "pop":0
	  },
	  {
		 "dt":1648026000,
		 "temp":311.34,
		 "feels_like":308.03,
		 "pressure":1004,
		 "humidity":5,
		 "dew_point":266.02,
		 "uvi":5.98,
		 "clouds":0,
		 "visibility":10000,
		 "wind_speed":4.95,
		 "wind_deg":292,
		 "wind_gust":6.87,
		 "weather":[
			{
			   "id":800,
			   "main":"Clear",
			   "description":"clear sky",
			   "icon":"01d"
			}
		 ],
		 "pop":0
	  },
	  {
		 "dt":1648029600,
		 "temp":311.3,
		 "feels_like":307.99,
		 "pressure":1003,
		 "humidity":5,
		 "dew_point":266.55,
		 "uvi":3.52,
		 "clouds":0,
		 "visibility":10000,
		 "wind_speed":5.79,
		 "wind_deg":287,
		 "wind_gust":7.14,
		 "weather":[
			{
			   "id":800,
			   "main":"Clear",
			   "description":"clear sky",
			   "icon":"01d"
			}
		 ],
		 "pop":0
	  },
	  {
		 "dt":1648033200,
		 "temp":310.76,
		 "feels_like":307.6,
		 "pressure":1003,
		 "humidity":6,
		 "dew_point":267.81,
		 "uvi":1.46,
		 "clouds":0,
		 "visibility":10000,
		 "wind_speed":6.43,
		 "wind_deg":280,
		 "wind_gust":7.24,
		 "weather":[
			{
			   "id":800,
			   "main":"Clear",
			   "description":"clear sky",
			   "icon":"01d"
			}
		 ],
		 "pop":0
	  },
	  {
		 "dt":1648036800,
		 "temp":309.85,
		 "feels_like":306.87,
		 "pressure":1003,
		 "humidity":7,
		 "dew_point":268.65,
		 "uvi":0.35,
		 "clouds":0,
		 "visibility":10000,
		 "wind_speed":5.99,
		 "wind_deg":273,
		 "wind_gust":6.85,
		 "weather":[
			{
			   "id":800,
			   "main":"Clear",
			   "description":"clear sky",
			   "icon":"01d"
			}
		 ],
		 "pop":0
	  },
	  {
		 "dt":1648040400,
		 "temp":307.79,
		 "feels_like":305.15,
		 "pressure":1003,
		 "humidity":8,
		 "dew_point":269.42,
		 "uvi":0,
		 "clouds":0,
		 "visibility":10000,
		 "wind_speed":5.34,
		 "wind_deg":273,
		 "wind_gust":9.32,
		 "weather":[
			{
			   "id":800,
			   "main":"Clear",
			   "description":"clear sky",
			   "icon":"01d"
			}
		 ],
		 "pop":0
	  },
	  {
		 "dt":1648044000,
		 "temp":306.68,
		 "feels_like":304.2,
		 "pressure":1004,
		 "humidity":9,
		 "dew_point":269.74,
		 "uvi":0,
		 "clouds":0,
		 "visibility":10000,
		 "wind_speed":4.42,
		 "wind_deg":274,
		 "wind_gust":9.28,
		 "weather":[
			{
			   "id":800,
			   "main":"Clear",
			   "description":"clear sky",
			   "icon":"01n"
			}
		 ],
		 "pop":0
	  },
	  {
		 "dt":1648047600,
		 "temp":305.75,
		 "feels_like":303.42,
		 "pressure":1005,
		 "humidity":10,
		 "dew_point":269.9,
		 "uvi":0,
		 "clouds":0,
		 "visibility":10000,
		 "wind_speed":3.68,
		 "wind_deg":274,
		 "wind_gust":8.36,
		 "weather":[
			{
			   "id":800,
			   "main":"Clear",
			   "description":"clear sky",
			   "icon":"01n"
			}
		 ],
		 "pop":0
	  },
	  {
		 "dt":1648051200,
		 "temp":304.72,
		 "feels_like":302.56,
		 "pressure":1006,
		 "humidity":10,
		 "dew_point":270.1,
		 "uvi":0,
		 "clouds":0,
		 "visibility":10000,
		 "wind_speed":2.99,
		 "wind_deg":270,
		 "wind_gust":6.38,
		 "weather":[
			{
			   "id":800,
			   "main":"Clear",
			   "description":"clear sky",
			   "icon":"01n"
			}
		 ],
		 "pop":0
	  },
	  {
		 "dt":1648054800,
		 "temp":303.52,
		 "feels_like":301.58,
		 "pressure":1006,
		 "humidity":11,
		 "dew_point":270.28,
		 "uvi":0,
		 "clouds":0,
		 "visibility":10000,
		 "wind_speed":3.85,
		 "wind_deg":255,
		 "wind_gust":8.3,
		 "weather":[
			{
			   "id":800,
			   "main":"Clear",
			   "description":"clear sky",
			   "icon":"01n"
			}
		 ],
		 "pop":0
	  },
	  {
		 "dt":1648058400,
		 "temp":302.64,
		 "feels_like":300.88,
		 "pressure":1006,
		 "humidity":12,
		 "dew_point":270.44,
		 "uvi":0,
		 "clouds":0,
		 "visibility":10000,
		 "wind_speed":3.06,
		 "wind_deg":257,
		 "wind_gust":8.06,
		 "weather":[
			{
			   "id":800,
			   "main":"Clear",
			   "description":"clear sky",
			   "icon":"01n"
			}
		 ],
		 "pop":0
	  },
	  {
		 "dt":1648062000,
		 "temp":301.72,
		 "feels_like":300.19,
		 "pressure":1005,
		 "humidity":13,
		 "dew_point":270.48,
		 "uvi":0,
		 "clouds":0,
		 "visibility":10000,
		 "wind_speed":1.85,
		 "wind_deg":274,
		 "wind_gust":5.11,
		 "weather":[
			{
			   "id":800,
			   "main":"Clear",
			   "description":"clear sky",
			   "icon":"01n"
			}
		 ],
		 "pop":0
	  },
	  {
		 "dt":1648065600,
		 "temp":300.64,
		 "feels_like":299.43,
		 "pressure":1005,
		 "humidity":14,
		 "dew_point":270.52,
		 "uvi":0,
		 "clouds":0,
		 "visibility":10000,
		 "wind_speed":1.8,
		 "wind_deg":277,
		 "wind_gust":5.18,
		 "weather":[
			{
			   "id":800,
			   "main":"Clear",
			   "description":"clear sky",
			   "icon":"01n"
			}
		 ],
		 "pop":0
	  },
	  {
		 "dt":1648069200,
		 "temp":300.16,
		 "feels_like":299.1,
		 "pressure":1004,
		 "humidity":14,
		 "dew_point":270.53,
		 "uvi":0,
		 "clouds":0,
		 "visibility":10000,
		 "wind_speed":2.02,
		 "wind_deg":293,
		 "wind_gust":4.42,
		 "weather":[
			{
			   "id":800,
			   "main":"Clear",
			   "description":"clear sky",
			   "icon":"01n"
			}
		 ],
		 "pop":0
	  },
	  {
		 "dt":1648072800,
		 "temp":299.56,
		 "feels_like":299.56,
		 "pressure":1004,
		 "humidity":14,
		 "dew_point":270.54,
		 "uvi":0,
		 "clouds":0,
		 "visibility":10000,
		 "wind_speed":2.19,
		 "wind_deg":296,
		 "wind_gust":5.65,
		 "weather":[
			{
			   "id":800,
			   "main":"Clear",
			   "description":"clear sky",
			   "icon":"01n"
			}
		 ],
		 "pop":0
	  },
	  {
		 "dt":1648076400,
		 "temp":298.9,
		 "feels_like":297.92,
		 "pressure":1004,
		 "humidity":15,
		 "dew_point":270.65,
		 "uvi":0,
		 "clouds":0,
		 "visibility":10000,
		 "wind_speed":1.54,
		 "wind_deg":274,
		 "wind_gust":3.36,
		 "weather":[
			{
			   "id":800,
			   "main":"Clear",
			   "description":"clear sky",
			   "icon":"01n"
			}
		 ],
		 "pop":0
	  },
	  {
		 "dt":1648080000,
		 "temp":298.59,
		 "feels_like":297.61,
		 "pressure":1004,
		 "humidity":16,
		 "dew_point":270.94,
		 "uvi":0,
		 "clouds":0,
		 "visibility":10000,
		 "wind_speed":1.15,
		 "wind_deg":258,
		 "wind_gust":1.58,
		 "weather":[
			{
			   "id":800,
			   "main":"Clear",
			   "description":"clear sky",
			   "icon":"01n"
			}
		 ],
		 "pop":0
	  },
	  {
		 "dt":1648083600,
		 "temp":298.23,
		 "feels_like":297.24,
		 "pressure":1005,
		 "humidity":17,
		 "dew_point":271.38,
		 "uvi":0,
		 "clouds":0,
		 "visibility":10000,
		 "wind_speed":1.55,
		 "wind_deg":286,
		 "wind_gust":2.91,
		 "weather":[
			{
			   "id":800,
			   "main":"Clear",
			   "description":"clear sky",
			   "icon":"01d"
			}
		 ],
		 "pop":0
	  },
	  {
		 "dt":1648087200,
		 "temp":299.32,
		 "feels_like":299.32,
		 "pressure":1005,
		 "humidity":17,
		 "dew_point":272.19,
		 "uvi":0.58,
		 "clouds":0,
		 "visibility":10000,
		 "wind_speed":0.93,
		 "wind_deg":245,
		 "wind_gust":1.86,
		 "weather":[
			{
			   "id":800,
			   "main":"Clear",
			   "description":"clear sky",
			   "icon":"01d"
			}
		 ],
		 "pop":0
	  },
	  {
		 "dt":1648090800,
		 "temp":301.88,
		 "feels_like":300.32,
		 "pressure":1006,
		 "humidity":15,
		 "dew_point":272.65,
		 "uvi":2.02,
		 "clouds":0,
		 "visibility":10000,
		 "wind_speed":2.12,
		 "wind_deg":254,
		 "wind_gust":3.28,
		 "weather":[
			{
			   "id":800,
			   "main":"Clear",
			   "description":"clear sky",
			   "icon":"01d"
			}
		 ],
		 "pop":0
	  },
	  {
		 "dt":1648094400,
		 "temp":304.47,
		 "feels_like":302.34,
		 "pressure":1007,
		 "humidity":13,
		 "dew_point":273.04,
		 "uvi":4.31,
		 "clouds":0,
		 "visibility":10000,
		 "wind_speed":3.28,
		 "wind_deg":260,
		 "wind_gust":5.05,
		 "weather":[
			{
			   "id":800,
			   "main":"Clear",
			   "description":"clear sky",
			   "icon":"01d"
			}
		 ],
		 "pop":0
	  },
	  {
		 "dt":1648098000,
		 "temp":306.67,
		 "feels_like":304.22,
		 "pressure":1007,
		 "humidity":12,
		 "dew_point":273.39,
		 "uvi":6.88,
		 "clouds":0,
		 "visibility":10000,
		 "wind_speed":3.76,
		 "wind_deg":259,
		 "wind_gust":6.06,
		 "weather":[
			{
			   "id":800,
			   "main":"Clear",
			   "description":"clear sky",
			   "icon":"01d"
			}
		 ],
		 "pop":0
	  },
	  {
		 "dt":1648101600,
		 "temp":308.81,
		 "feels_like":306.07,
		 "pressure":1005,
		 "humidity":10,
		 "dew_point":272.29,
		 "uvi":8.83,
		 "clouds":0,
		 "visibility":10000,
		 "wind_speed":3.87,
		 "wind_deg":254,
		 "wind_gust":7.13,
		 "weather":[
			{
			   "id":800,
			   "main":"Clear",
			   "description":"clear sky",
			   "icon":"01d"
			}
		 ],
		 "pop":0
	  },
	  {
		 "dt":1648105200,
		 "temp":310.15,
		 "feels_like":307.22,
		 "pressure":1004,
		 "humidity":9,
		 "dew_point":271.92,
		 "uvi":9.43,
		 "clouds":0,
		 "visibility":10000,
		 "wind_speed":4.8,
		 "wind_deg":258,
		 "wind_gust":7.06,
		 "weather":[
			{
			   "id":800,
			   "main":"Clear",
			   "description":"clear sky",
			   "icon":"01d"
			}
		 ],
		 "pop":0
	  },
	  {
		 "dt":1648108800,
		 "temp":310.89,
		 "feels_like":307.82,
		 "pressure":1003,
		 "humidity":8,
		 "dew_point":271.46,
		 "uvi":8.44,
		 "clouds":0,
		 "visibility":10000,
		 "wind_speed":5.12,
		 "wind_deg":261,
		 "wind_gust":8.28,
		 "weather":[
			{
			   "id":800,
			   "main":"Clear",
			   "description":"clear sky",
			   "icon":"01d"
			}
		 ],
		 "pop":0
	  },
	  {
		 "dt":1648112400,
		 "temp":311.3,
		 "feels_like":308.1,
		 "pressure":1001,
		 "humidity":7,
		 "dew_point":270.45,
		 "uvi":6.25,
		 "clouds":0,
		 "visibility":10000,
		 "wind_speed":5.52,
		 "wind_deg":261,
		 "wind_gust":8.29,
		 "weather":[
			{
			   "id":800,
			   "main":"Clear",
			   "description":"clear sky",
			   "icon":"01d"
			}
		 ],
		 "pop":0
	  },
	  {
		 "dt":1648116000,
		 "temp":311.32,
		 "feels_like":308.12,
		 "pressure":1001,
		 "humidity":7,
		 "dew_point":269.6,
		 "uvi":3.6,
		 "clouds":1,
		 "visibility":10000,
		 "wind_speed":5.79,
		 "wind_deg":259,
		 "wind_gust":8.09,
		 "weather":[
			{
			   "id":800,
			   "main":"Clear",
			   "description":"clear sky",
			   "icon":"01d"
			}
		 ],
		 "pop":0
	  },
	  {
		 "dt":1648119600,
		 "temp":310.88,
		 "feels_like":307.75,
		 "pressure":1000,
		 "humidity":7,
		 "dew_point":268.93,
		 "uvi":1.49,
		 "clouds":2,
		 "visibility":10000,
		 "wind_speed":5.94,
		 "wind_deg":261,
		 "wind_gust":7.8,
		 "weather":[
			{
			   "id":800,
			   "main":"Clear",
			   "description":"clear sky",
			   "icon":"01d"
			}
		 ],
		 "pop":0
	  },
	  {
		 "dt":1648123200,
		 "temp":310.13,
		 "feels_like":307.11,
		 "pressure":1000,
		 "humidity":7,
		 "dew_point":268.48,
		 "uvi":0.37,
		 "clouds":2,
		 "visibility":10000,
		 "wind_speed":5.15,
		 "wind_deg":262,
		 "wind_gust":7.32,
		 "weather":[
			{
			   "id":800,
			   "main":"Clear",
			   "description":"clear sky",
			   "icon":"01d"
			}
		 ],
		 "pop":0
	  },
	  {
		 "dt":1648126800,
		 "temp":307.73,
		 "feels_like":305.09,
		 "pressure":1001,
		 "humidity":8,
		 "dew_point":268.13,
		 "uvi":0,
		 "clouds":0,
		 "visibility":10000,
		 "wind_speed":3.82,
		 "wind_deg":263,
		 "wind_gust":8.02,
		 "weather":[
			{
			   "id":800,
			   "main":"Clear",
			   "description":"clear sky",
			   "icon":"01d"
			}
		 ],
		 "pop":0
	  },
	  {
		 "dt":1648130400,
		 "temp":306.01,
		 "feels_like":303.66,
		 "pressure":1002,
		 "humidity":8,
		 "dew_point":267.85,
		 "uvi":0,
		 "clouds":0,
		 "visibility":10000,
		 "wind_speed":2.94,
		 "wind_deg":261,
		 "wind_gust":7.17,
		 "weather":[
			{
			   "id":800,
			   "main":"Clear",
			   "description":"clear sky",
			   "icon":"01n"
			}
		 ],
		 "pop":0
	  },
	  {
		 "dt":1648134000,
		 "temp":304.76,
		 "feels_like":302.61,
		 "pressure":1002,
		 "humidity":9,
		 "dew_point":267.58,
		 "uvi":0,
		 "clouds":0,
		 "visibility":10000,
		 "wind_speed":2.58,
		 "wind_deg":255,
		 "wind_gust":6.81,
		 "weather":[
			{
			   "id":800,
			   "main":"Clear",
			   "description":"clear sky",
			   "icon":"01n"
			}
		 ],
		 "pop":0
	  },
	  {
		 "dt":1648137600,
		 "temp":303.87,
		 "feels_like":301.89,
		 "pressure":1003,
		 "humidity":9,
		 "dew_point":267.83,
		 "uvi":0,
		 "clouds":0,
		 "visibility":10000,
		 "wind_speed":2.99,
		 "wind_deg":258,
		 "wind_gust":7.21,
		 "weather":[
			{
			   "id":800,
			   "main":"Clear",
			   "description":"clear sky",
			   "icon":"01n"
			}
		 ],
		 "pop":0
	  },
	  {
		 "dt":1648141200,
		 "temp":303.09,
		 "feels_like":301.24,
		 "pressure":1003,
		 "humidity":11,
		 "dew_point":268.94,
		 "uvi":0,
		 "clouds":0,
		 "visibility":10000,
		 "wind_speed":2.29,
		 "wind_deg":233,
		 "wind_gust":4.6,
		 "weather":[
			{
			   "id":800,
			   "main":"Clear",
			   "description":"clear sky",
			   "icon":"01n"
			}
		 ],
		 "pop":0
	  },
	  {
		 "dt":1648144800,
		 "temp":302.42,
		 "feels_like":300.72,
		 "pressure":1003,
		 "humidity":12,
		 "dew_point":270.06,
		 "uvi":0,
		 "clouds":0,
		 "visibility":10000,
		 "wind_speed":2.54,
		 "wind_deg":248,
		 "wind_gust":6.78,
		 "weather":[
			{
			   "id":800,
			   "main":"Clear",
			   "description":"clear sky",
			   "icon":"01n"
			}
		 ],
		 "pop":0
	  }
   ]
}
